{"seq_groups": 1, "hash": "2de4ce342fc1b5498250add72d7ad6c5", "tri_count": "7848", "events": [{"seq": "12", "frame": "0", "file": "player/bxa00dead011.wav"}, {"seq": "13", "frame": "0", "file": "player/bxa00dead021.wav"}, {"seq": "14", "frame": "0", "file": "player/bxa00dead021.wav"}, {"seq": "15", "frame": "0", "file": "player/bxa00dead011.wav"}, {"seq": "16", "frame": "0", "file": "player/bxa00dead021.wav"}, {"seq": "17", "frame": "0", "file": "player/bxa00dead011.wav"}, {"seq": "18", "frame": "0", "file": "player/bxa00dead021.wav"}]}